pybeehive/__init__.py
pybeehive/core.py
pybeehive/hive.py
pybeehive/logging.py
pybeehive/socket.py
pybeehive-0.1.4.dist-info/METADATA
pybeehive-0.1.4.dist-info/RECORD
pybeehive-0.1.4.dist-info/WHEEL
pybeehive-0.1.4.dist-info/top_level.txt
