Metadata-Version: 2.1
Name: pybeehive
Version: 0.1.4
Summary: A lightweight, event-driven concurrency library with bees!
Home-page: https://github.com/sentrip/pybeehive
Author: Djordje Pepic
Author-email: djordje.m.pepic@gmail.com
License: GNU General Public License v3
Keywords: pybeehive
Platform: UNKNOWN
Classifier: Development Status :: 2 - Pre-Alpha
Classifier: Intended Audience :: Developers
Classifier: License :: OSI Approved :: GNU General Public License v3 (GPLv3)
Classifier: Natural Language :: English
Classifier: Programming Language :: Python :: 2
Classifier: Programming Language :: Python :: 2.7
Classifier: Programming Language :: Python :: 3
Classifier: Programming Language :: Python :: 3.4
Classifier: Programming Language :: Python :: 3.5
Classifier: Programming Language :: Python :: 3.6
Requires-Dist: pyzmq (>=17.0.0)
